doc_loader/__init__.py
doc_loader/doc_loader.cpython-313-x86_64-linux-gnu.so
extracteur_docs_rs-0.3.2.dist-info/METADATA
extracteur_docs_rs-0.3.2.dist-info/WHEEL
extracteur_docs_rs-0.3.2.dist-info/licenses/LICENSE
extracteur_docs_rs-0.3.2.dist-info/RECORD
