Metadata-Version: 2.4
Name: extracteur-docs-rs
Version: 0.3.2
Classifier: Development Status :: 4 - Beta
Classifier: Intended Audience :: Developers
Classifier: License :: OSI Approved :: MIT License
Classifier: Programming Language :: Python :: 3
Classifier: Programming Language :: Python :: 3.9
Classifier: Programming Language :: Python :: 3.10
Classifier: Programming Language :: Python :: 3.11
Classifier: Programming Language :: Python :: 3.12
Classifier: Programming Language :: Python :: 3.13
Classifier: Programming Language :: Rust
Classifier: Topic :: Text Processing
Classifier: Topic :: Software Development :: Libraries
Classifier: Topic :: Scientific/Engineering :: Information Analysis
Requires-Dist: pytest>=7.0 ; extra == 'dev'
Requires-Dist: pytest-benchmark>=4.0 ; extra == 'dev'
Requires-Dist: black>=22.0 ; extra == 'dev'
Requires-Dist: mypy>=1.0 ; extra == 'dev'
Requires-Dist: pandas>=1.5.0 ; extra == 'examples'
Requires-Dist: numpy>=1.21.0 ; extra == 'examples'
Requires-Dist: sentence-transformers>=2.0.0 ; extra == 'examples'
Requires-Dist: flask>=2.0.0 ; extra == 'examples'
Provides-Extra: dev
Provides-Extra: examples
License-File: LICENSE
Summary: Un toolkit complet pour extraire et traiter la documentation depuis plusieurs formats de fichiers (PDF, TXT, JSON, CSV, DOCX) avec des bindings Python
Keywords: document,processing,pdf,text,extraction
Home-Page: https://github.com/WillIsback/doc_loader
Author: WillIsback <will@example.com>
Author-email: WillIsback <will@example.com>
License: MIT
Requires-Python: >=3.9
Project-URL: Repository, https://github.com/WillIsback/doc_loader
Project-URL: Documentation, https://willisback.github.io/doc_loader/
Project-URL: Homepage, https://github.com/WillIsback/doc_loader
